pishield/__init__.py
pishield/shield_layer.py
pishield/linear_requirements/__init__.py
pishield/linear_requirements/classes.py
pishield/linear_requirements/compute_sets_of_constraints.py
pishield/linear_requirements/correct_predictions.py
pishield/linear_requirements/feature_orderings.py
pishield/linear_requirements/manual_correct.py
pishield/linear_requirements/parser.py
pishield/linear_requirements/shield_layer.py
pishield/linear_requirements/utils.py
pishield/propositional_requirements/__init__.py
pishield/propositional_requirements/clause.py
pishield/propositional_requirements/clauses_group.py
pishield/propositional_requirements/constraint.py
pishield/propositional_requirements/constraints_group.py
pishield/propositional_requirements/constraints_module.py
pishield/propositional_requirements/detection_threshold.py
pishield/propositional_requirements/literal.py
pishield/propositional_requirements/profiler.py
pishield/propositional_requirements/shield_layer.py
pishield/propositional_requirements/slicer.py
pishield/propositional_requirements/strong_coherency.py
pishield/propositional_requirements/util.py
pishield-1.0.0.dist-info/LICENSE.txt
pishield-1.0.0.dist-info/METADATA
pishield-1.0.0.dist-info/WHEEL
pishield-1.0.0.dist-info/top_level.txt
pishield-1.0.0.dist-info/RECORD
