Metadata-Version: 2.1
Name: pishield
Version: 1.0.0
Summary: A NeSy Framework for Learning with Requirements
Home-page: https://github.com/mihaela-stoian/PiShield
Author-email: mihaela.stoian@cs.ox.ac.uk
Project-URL: Bug Reports, https://github.com/mihaela-stoian/PiShield/issues
Project-URL: Source, https://github.com/mihaela-stoian/PiShield/
Project-URL: Website, https://sites.google.com/view/pishield
Requires-Python: >=3.8.0, <4
License-File: LICENSE.txt
Requires-Dist: numpy
Requires-Dist: torch
